{
  "day": "2025_11_25",
  "date_iso": "2025-11-25",
  "threshold": 0.85,
  "n_phrases": 8,
  "n_motifs": 21,
  "phrases": [
    {
      "start_i": 0,
      "end_i": 721,
      "shape": "FLATLINE",
      "r": 0.0,
      "skew": "NONE",
      "mean_sigma": 7.446453469532126,
      "motifs": [
        {
          "start_i": 0,
          "end_i": 721,
          "shape": "FLATLINE",
          "r": 0.0,
          "skew": "NONE",
          "mean_sigma": 4.797227147353005,
          "start_ts": 1764028800,
          "end_ts": 1764032600,
          "length_min": 63.3
        }
      ],
      "start_ts": 1764028800,
      "end_ts": 1764032600,
      "length_min": 63.3
    },
    {
      "start_i": 1065,
      "end_i": 1401,
      "shape": "GENTLE_LINEAR_DOWN",
      "r": 0.9227841744446489,
      "skew": "NONE",
      "mean_sigma": 10.74814057287739,
      "motifs": [
        {
          "start_i": 1065,
          "end_i": 1401,
          "shape": "GENTLE_LINEAR_DOWN",
          "r": 0.9793908723379243,
          "skew": "NONE",
          "mean_sigma": 7.866498935935114,
          "start_ts": 1764034555,
          "end_ts": 1764036450,
          "length_min": 31.6
        }
      ],
      "start_ts": 1764034555,
      "end_ts": 1764036450,
      "length_min": 31.6
    },
    {
      "start_i": 1401,
      "end_i": 2041,
      "shape": "GENTLE_CONVEX_UP",
      "r": 0.8822097042268738,
      "skew": "SYMMETRIC",
      "mean_sigma": 10.12426168389996,
      "motifs": [
        {
          "start_i": 1401,
          "end_i": 2041,
          "shape": "GENTLE_LINEAR_UP",
          "r": 0.945432669284831,
          "skew": "NONE",
          "mean_sigma": 7.272641159364308,
          "start_ts": 1764036450,
          "end_ts": 1764040445,
          "length_min": 66.6
        }
      ],
      "start_ts": 1764036450,
      "end_ts": 1764040445,
      "length_min": 66.6
    },
    {
      "start_i": 2041,
      "end_i": 3456,
      "shape": "FLATLINE",
      "r": 0.4888928341571696,
      "skew": "NONE",
      "mean_sigma": 9.775208192649371,
      "motifs": [
        {
          "start_i": 2041,
          "end_i": 3297,
          "shape": "NOISE",
          "r": 0.7621498189094769,
          "skew": "NONE",
          "mean_sigma": 7.529224163324454,
          "start_ts": 1764040445,
          "end_ts": 1764048500,
          "length_min": 134.2
        },
        {
          "start_i": 3297,
          "end_i": 3456,
          "shape": "FLATLINE",
          "r": 0.7853817917814224,
          "skew": "NONE",
          "mean_sigma": 9.691706146813619,
          "start_ts": 1764048500,
          "end_ts": 1764049500,
          "length_min": 16.7
        }
      ],
      "start_ts": 1764040445,
      "end_ts": 1764049500,
      "length_min": 150.9
    },
    {
      "start_i": 3456,
      "end_i": 7913,
      "shape": "GENTLE_LINEAR_DOWN",
      "r": 0.9771693382304891,
      "skew": "NONE",
      "mean_sigma": 18.945538022220205,
      "motifs": [
        {
          "start_i": 3456,
          "end_i": 4916,
          "shape": "GENTLE_CONVEX_DOWN",
          "r": 0.8735725799624819,
          "skew": "FRONT_SKEWED",
          "mean_sigma": 8.670310235503603,
          "start_ts": 1764049500,
          "end_ts": 1764058140,
          "length_min": 144.0
        },
        {
          "start_i": 4916,
          "end_i": 5482,
          "shape": "FLATLINE",
          "r": 0.0,
          "skew": "NONE",
          "mean_sigma": 11.59966652345337,
          "start_ts": 1764058140,
          "end_ts": 1764061100,
          "length_min": 49.3
        },
        {
          "start_i": 5482,
          "end_i": 6634,
          "shape": "GENTLE_CONVEX_DOWN",
          "r": 0.917089775509512,
          "skew": "SYMMETRIC",
          "mean_sigma": 16.950290427659844,
          "start_ts": 1764061100,
          "end_ts": 1764067080,
          "length_min": 99.7
        },
        {
          "start_i": 6634,
          "end_i": 7545,
          "shape": "NOISE",
          "r": 0.6355408792981717,
          "skew": "NONE",
          "mean_sigma": 10.448391350984421,
          "start_ts": 1764067080,
          "end_ts": 1764071955,
          "length_min": 81.2
        },
        {
          "start_i": 7545,
          "end_i": 7733,
          "shape": "STEEP_CONVEX_UP",
          "r": 0.9329716961568906,
          "skew": "BACK_SKEWED",
          "mean_sigma": 16.981488162770844,
          "start_ts": 1764071955,
          "end_ts": 1764072900,
          "length_min": 15.8
        },
        {
          "start_i": 7733,
          "end_i": 7793,
          "shape": "FLATLINE",
          "r": 0.6648450374214705,
          "skew": "NONE",
          "mean_sigma": 29.919349934725872,
          "start_ts": 1764072900,
          "end_ts": 1764073200,
          "length_min": 5.0
        },
        {
          "start_i": 7793,
          "end_i": 7913,
          "shape": "STEEP_LINEAR_UP",
          "r": 0.8689013949608243,
          "skew": "NONE",
          "mean_sigma": 29.209970166288535,
          "start_ts": 1764073200,
          "end_ts": 1764073800,
          "length_min": 10.0
        }
      ],
      "start_ts": 1764049500,
      "end_ts": 1764073800,
      "length_min": 405.0
    },
    {
      "start_i": 7913,
      "end_i": 9349,
      "shape": "GENTLE_CONCAVE_UP",
      "r": 0.9479716769859862,
      "skew": "SYMMETRIC",
      "mean_sigma": 28.684252118131564,
      "motifs": [
        {
          "start_i": 7913,
          "end_i": 8812,
          "shape": "NOISE",
          "r": 0.8397675804054767,
          "skew": "NONE",
          "mean_sigma": 16.256544329092208,
          "start_ts": 1764073800,
          "end_ts": 1764078315,
          "length_min": 75.2
        },
        {
          "start_i": 8812,
          "end_i": 9349,
          "shape": "STEEP_LINEAR_DOWN",
          "r": 0.9731734654950367,
          "skew": "NONE",
          "mean_sigma": 21.9865377326879,
          "start_ts": 1764078315,
          "end_ts": 1764081005,
          "length_min": 44.8
        }
      ],
      "start_ts": 1764073800,
      "end_ts": 1764081005,
      "length_min": 120.1
    },
    {
      "start_i": 9349,
      "end_i": 11328,
      "shape": "GENTLE_LINEAR_DOWN",
      "r": 0.9585407789175138,
      "skew": "NONE",
      "mean_sigma": 58.433989956936834,
      "motifs": [
        {
          "start_i": 9349,
          "end_i": 10488,
          "shape": "NOISE",
          "r": 0.8268603067710382,
          "skew": "NONE",
          "mean_sigma": 51.836857450081446,
          "start_ts": 1764081005,
          "end_ts": 1764086700,
          "length_min": 94.9
        },
        {
          "start_i": 10488,
          "end_i": 11328,
          "shape": "STEEP_CONVEX_UP",
          "r": 0.9686351193205972,
          "skew": "BACK_SKEWED",
          "mean_sigma": 28.10128226426084,
          "start_ts": 1764086700,
          "end_ts": 1764090900,
          "length_min": 70.0
        }
      ],
      "start_ts": 1764081005,
      "end_ts": 1764090900,
      "length_min": 164.9
    },
    {
      "start_i": 11328,
      "end_i": 15248,
      "shape": "STEEP_CONCAVE_UP",
      "r": 0.9865894051182468,
      "skew": "FRONT_SKEWED",
      "mean_sigma": 53.198163930286555,
      "motifs": [
        {
          "start_i": 11328,
          "end_i": 12948,
          "shape": "STEEP_CONCAVE_UP",
          "r": 0.9089332206203982,
          "skew": "FRONT_SKEWED",
          "mean_sigma": 24.628789862155937,
          "start_ts": 1764090900,
          "end_ts": 1764099000,
          "length_min": 135.0
        },
        {
          "start_i": 12948,
          "end_i": 13608,
          "shape": "NOISE",
          "r": 0.42617050667676665,
          "skew": "NONE",
          "mean_sigma": 23.888230447235593,
          "start_ts": 1764099000,
          "end_ts": 1764102300,
          "length_min": 55.0
        },
        {
          "start_i": 13608,
          "end_i": 14748,
          "shape": "STEEP_CONCAVE_UP",
          "r": 0.8955009063010981,
          "skew": "SYMMETRIC",
          "mean_sigma": 16.986578822347038,
          "start_ts": 1764102300,
          "end_ts": 1764111975,
          "length_min": 161.2
        },
        {
          "start_i": 14748,
          "end_i": 15148,
          "shape": "GENTLE_LINEAR_UP",
          "r": 0.9928848384356851,
          "skew": "NONE",
          "mean_sigma": 8.355179645344444,
          "start_ts": 1764111975,
          "end_ts": 1764114570,
          "length_min": 43.2
        },
        {
          "start_i": 15151,
          "end_i": 15248,
          "shape": "FLATLINE",
          "r": 0.8609160647753272,
          "skew": "NONE",
          "mean_sigma": 5.463811405441072,
          "start_ts": 1764114600,
          "end_ts": 1764115195,
          "length_min": 9.9
        }
      ],
      "start_ts": 1764090900,
      "end_ts": 1764115195,
      "length_min": 404.9
    }
  ]
}