{
  "day": "2025_09_05",
  "date_iso": "2025-09-05",
  "threshold": 0.85,
  "n_phrases": 6,
  "n_motifs": 14,
  "phrases": [
    {
      "start_i": 0,
      "end_i": 721,
      "shape": "NOISE",
      "r": -2.0,
      "skew": "NONE",
      "mean_sigma": 3.487815051667849,
      "motifs": [
        {
          "start_i": 0,
          "end_i": 721,
          "shape": "NOISE",
          "r": -2.0,
          "skew": "NONE",
          "mean_sigma": 5.96196481772087,
          "start_ts": 1757030400,
          "end_ts": 1757034845,
          "length_min": 74.1
        }
      ],
      "start_ts": 1757030400,
      "end_ts": 1757034845,
      "length_min": 74.1
    },
    {
      "start_i": 1040,
      "end_i": 6999,
      "shape": "GENTLE_LINEAR_UP",
      "r": 0.9868114555711439,
      "skew": "NONE",
      "mean_sigma": 8.840938771706867,
      "motifs": [
        {
          "start_i": 1040,
          "end_i": 3793,
          "shape": "GENTLE_LINEAR_UP",
          "r": 0.9395424797878181,
          "skew": "NONE",
          "mean_sigma": 4.776902844935401,
          "start_ts": 1757037170,
          "end_ts": 1757057100,
          "length_min": 332.2
        },
        {
          "start_i": 3793,
          "end_i": 4513,
          "shape": "NOISE",
          "r": 0.5181709210191887,
          "skew": "NONE",
          "mean_sigma": 5.700495438459754,
          "start_ts": 1757057100,
          "end_ts": 1757061245,
          "length_min": 69.1
        },
        {
          "start_i": 4513,
          "end_i": 6777,
          "shape": "GENTLE_CONCAVE_UP",
          "r": 0.9543012486912538,
          "skew": "BACK_SKEWED",
          "mean_sigma": 4.788693473468036,
          "start_ts": 1757061245,
          "end_ts": 1757074410,
          "length_min": 219.4
        },
        {
          "start_i": 6777,
          "end_i": 6999,
          "shape": "GENTLE_CONVEX_DOWN",
          "r": 0.9329086561410693,
          "skew": "BACK_SKEWED",
          "mean_sigma": 5.803348780847562,
          "start_ts": 1757074410,
          "end_ts": 1757075530,
          "length_min": 18.7
        }
      ],
      "start_ts": 1757037170,
      "end_ts": 1757075530,
      "length_min": 639.3
    },
    {
      "start_i": 6999,
      "end_i": 7153,
      "shape": "FLATLINE",
      "r": 0.0,
      "skew": "NONE",
      "mean_sigma": 7.153834982381986,
      "motifs": [
        {
          "start_i": 6999,
          "end_i": 7153,
          "shape": "STEEP_LINEAR_UP",
          "r": 0.9232707848513986,
          "skew": "NONE",
          "mean_sigma": 15.556243667116538,
          "start_ts": 1757075530,
          "end_ts": 1757076300,
          "length_min": 12.8
        }
      ],
      "start_ts": 1757075530,
      "end_ts": 1757076300,
      "length_min": 12.8
    },
    {
      "start_i": 7153,
      "end_i": 8413,
      "shape": "GENTLE_CONCAVE_UP",
      "r": 0.9088579424581172,
      "skew": "BACK_SKEWED",
      "mean_sigma": 37.12271835165112,
      "motifs": [
        {
          "start_i": 7153,
          "end_i": 8233,
          "shape": "NOISE",
          "r": 0.8429656937253395,
          "skew": "NONE",
          "mean_sigma": 23.56825910288163,
          "start_ts": 1757076300,
          "end_ts": 1757081700,
          "length_min": 90.0
        },
        {
          "start_i": 8233,
          "end_i": 8413,
          "shape": "STEEP_LINEAR_DOWN",
          "r": 0.9402513326406068,
          "skew": "NONE",
          "mean_sigma": 60.65592481155812,
          "start_ts": 1757081700,
          "end_ts": 1757082600,
          "length_min": 15.0
        }
      ],
      "start_ts": 1757076300,
      "end_ts": 1757082600,
      "length_min": 105.0
    },
    {
      "start_i": 8413,
      "end_i": 11113,
      "shape": "STEEP_CONVEX_DOWN",
      "r": 0.9650724028918563,
      "skew": "BACK_SKEWED",
      "mean_sigma": 85.07465368935681,
      "motifs": [
        {
          "start_i": 8413,
          "end_i": 9553,
          "shape": "STEEP_CONVEX_DOWN",
          "r": 0.8872378132391106,
          "skew": "FRONT_SKEWED",
          "mean_sigma": 51.354181434400665,
          "start_ts": 1757082600,
          "end_ts": 1757088300,
          "length_min": 95.0
        },
        {
          "start_i": 9553,
          "end_i": 10273,
          "shape": "FLATLINE",
          "r": 0.0,
          "skew": "NONE",
          "mean_sigma": 16.706677936168763,
          "start_ts": 1757088300,
          "end_ts": 1757091900,
          "length_min": 60.0
        },
        {
          "start_i": 10273,
          "end_i": 10573,
          "shape": "GENTLE_LINEAR_UP",
          "r": 0.9315817816710674,
          "skew": "NONE",
          "mean_sigma": 17.078579050753046,
          "start_ts": 1757091900,
          "end_ts": 1757093400,
          "length_min": 25.0
        },
        {
          "start_i": 10573,
          "end_i": 10933,
          "shape": "GENTLE_CONCAVE_DOWN",
          "r": 0.9051309883355882,
          "skew": "SYMMETRIC",
          "mean_sigma": 16.1369100228987,
          "start_ts": 1757093400,
          "end_ts": 1757095200,
          "length_min": 30.0
        },
        {
          "start_i": 10933,
          "end_i": 11113,
          "shape": "STEEP_LINEAR_DOWN",
          "r": 0.9439929491538919,
          "skew": "NONE",
          "mean_sigma": 16.325976683924846,
          "start_ts": 1757095200,
          "end_ts": 1757096100,
          "length_min": 15.0
        }
      ],
      "start_ts": 1757082600,
      "end_ts": 1757096100,
      "length_min": 225.0
    },
    {
      "start_i": 11113,
      "end_i": 13023,
      "shape": "GENTLE_LINEAR_UP",
      "r": 0.965320379655855,
      "skew": "NONE",
      "mean_sigma": 20.066643931535587,
      "motifs": [
        {
          "start_i": 11113,
          "end_i": 13023,
          "shape": "GENTLE_CONCAVE_UP",
          "r": 0.979013546644428,
          "skew": "FRONT_SKEWED",
          "mean_sigma": 10.71844452081661,
          "start_ts": 1757096100,
          "end_ts": 1757105995,
          "length_min": 164.9
        }
      ],
      "start_ts": 1757096100,
      "end_ts": 1757105995,
      "length_min": 164.9
    }
  ]
}