{
  "day": "2026_01_23",
  "date_iso": "2026-01-23",
  "threshold": 0.85,
  "n_phrases": 7,
  "n_motifs": 14,
  "phrases": [
    {
      "start_i": 0,
      "end_i": 721,
      "shape": "NOISE",
      "r": -2.0,
      "skew": "NONE",
      "mean_sigma": 7.742165144310591,
      "motifs": [
        {
          "start_i": 0,
          "end_i": 721,
          "shape": "NOISE",
          "r": -2.0,
          "skew": "NONE",
          "mean_sigma": 9.214773948230038,
          "start_ts": 1769126400,
          "end_ts": 1769130661,
          "length_min": 71.0
        }
      ],
      "start_ts": 1769126400,
      "end_ts": 1769130661,
      "length_min": 71.0
    },
    {
      "start_i": 1037,
      "end_i": 4567,
      "shape": "GENTLE_CONCAVE_UP",
      "r": 0.9732841592805721,
      "skew": "BACK_SKEWED",
      "mean_sigma": 13.663060303899439,
      "motifs": [
        {
          "start_i": 1037,
          "end_i": 4176,
          "shape": "GENTLE_LINEAR_UP",
          "r": 0.944493202184346,
          "skew": "NONE",
          "mean_sigma": 6.554304980592081,
          "start_ts": 1769132396,
          "end_ts": 1769153871,
          "length_min": 357.9
        },
        {
          "start_i": 4176,
          "end_i": 4567,
          "shape": "STEEP_CONCAVE_DOWN",
          "r": 0.9875409729727662,
          "skew": "BACK_SKEWED",
          "mean_sigma": 10.844773874349139,
          "start_ts": 1769153871,
          "end_ts": 1769156100,
          "length_min": 37.1
        }
      ],
      "start_ts": 1769132396,
      "end_ts": 1769156100,
      "length_min": 395.1
    },
    {
      "start_i": 4567,
      "end_i": 7144,
      "shape": "STEEP_LINEAR_DOWN",
      "r": 0.9747790103761039,
      "skew": "NONE",
      "mean_sigma": 40.70273111394885,
      "motifs": [
        {
          "start_i": 4567,
          "end_i": 6602,
          "shape": "STEEP_CONVEX_DOWN",
          "r": 0.9748340855704227,
          "skew": "BACK_SKEWED",
          "mean_sigma": 16.249588800490255,
          "start_ts": 1769156100,
          "end_ts": 1769166900,
          "length_min": 180.0
        },
        {
          "start_i": 6602,
          "end_i": 7144,
          "shape": "STEEP_CONCAVE_UP",
          "r": 0.9513177112662563,
          "skew": "SYMMETRIC",
          "mean_sigma": 24.194523871619857,
          "start_ts": 1769166900,
          "end_ts": 1769169750,
          "length_min": 47.5
        }
      ],
      "start_ts": 1769156100,
      "end_ts": 1769169750,
      "length_min": 227.5
    },
    {
      "start_i": 7144,
      "end_i": 8684,
      "shape": "GENTLE_LINEAR_UP",
      "r": 0.9305169927524022,
      "skew": "NONE",
      "mean_sigma": 30.13694323804577,
      "motifs": [
        {
          "start_i": 7144,
          "end_i": 8065,
          "shape": "NOISE",
          "r": 0.7034438972531236,
          "skew": "NONE",
          "mean_sigma": 12.642635046144841,
          "start_ts": 1769169750,
          "end_ts": 1769174645,
          "length_min": 81.6
        },
        {
          "start_i": 8065,
          "end_i": 8195,
          "shape": "STEEP_CONCAVE_DOWN",
          "r": 0.8945092095760303,
          "skew": "BACK_SKEWED",
          "mean_sigma": 13.170172613754872,
          "start_ts": 1769174645,
          "end_ts": 1769175300,
          "length_min": 10.9
        },
        {
          "start_i": 8195,
          "end_i": 8312,
          "shape": "FLATLINE",
          "r": 0.8716323326229403,
          "skew": "BACK_SKEWED",
          "mean_sigma": 20.46372012833293,
          "start_ts": 1769175300,
          "end_ts": 1769175900,
          "length_min": 10.0
        },
        {
          "start_i": 8312,
          "end_i": 8684,
          "shape": "STEEP_LINEAR_DOWN",
          "r": 0.9806141290920699,
          "skew": "NONE",
          "mean_sigma": 15.875860258356186,
          "start_ts": 1769175900,
          "end_ts": 1769177777,
          "length_min": 31.3
        }
      ],
      "start_ts": 1769169750,
      "end_ts": 1769177777,
      "length_min": 133.8
    },
    {
      "start_i": 8684,
      "end_i": 9388,
      "shape": "FLATLINE",
      "r": 0.0,
      "skew": "NONE",
      "mean_sigma": 24.476812564079655,
      "motifs": [
        {
          "start_i": 8684,
          "end_i": 9388,
          "shape": "STEEP_CONVEX_UP",
          "r": 0.9936869342427567,
          "skew": "BACK_SKEWED",
          "mean_sigma": 20.241176569394966,
          "start_ts": 1769177777,
          "end_ts": 1769181300,
          "length_min": 58.7
        }
      ],
      "start_ts": 1769177777,
      "end_ts": 1769181300,
      "length_min": 58.7
    },
    {
      "start_i": 9388,
      "end_i": 12088,
      "shape": "STEEP_CONCAVE_UP",
      "r": 0.9653516275851763,
      "skew": "BACK_SKEWED",
      "mean_sigma": 67.80465379160104,
      "motifs": [
        {
          "start_i": 9388,
          "end_i": 10768,
          "shape": "STEEP_CONCAVE_UP",
          "r": 0.9596836609834581,
          "skew": "FRONT_SKEWED",
          "mean_sigma": 32.41838209571471,
          "start_ts": 1769181300,
          "end_ts": 1769188200,
          "length_min": 115.0
        },
        {
          "start_i": 10768,
          "end_i": 12088,
          "shape": "STEEP_LINEAR_DOWN",
          "r": 0.8946983401835547,
          "skew": "NONE",
          "mean_sigma": 21.95811653224026,
          "start_ts": 1769188200,
          "end_ts": 1769194800,
          "length_min": 110.0
        }
      ],
      "start_ts": 1769181300,
      "end_ts": 1769194800,
      "length_min": 225.0
    },
    {
      "start_i": 12088,
      "end_i": 14205,
      "shape": "GENTLE_CONVEX_DOWN",
      "r": 0.9643152270701842,
      "skew": "SYMMETRIC",
      "mean_sigma": 26.002163889143112,
      "motifs": [
        {
          "start_i": 12088,
          "end_i": 12928,
          "shape": "NOISE",
          "r": 0.5316969067106548,
          "skew": "NONE",
          "mean_sigma": 13.196953258381816,
          "start_ts": 1769194800,
          "end_ts": 1769199000,
          "length_min": 70.0
        },
        {
          "start_i": 12928,
          "end_i": 14205,
          "shape": "GENTLE_CONCAVE_DOWN",
          "r": 0.9550782609448178,
          "skew": "BACK_SKEWED",
          "mean_sigma": 14.125701010859391,
          "start_ts": 1769199000,
          "end_ts": 1769205595,
          "length_min": 109.9
        }
      ],
      "start_ts": 1769194800,
      "end_ts": 1769205595,
      "length_min": 179.9
    }
  ]
}